delpinos/rabbitmq/api/config.py
delpinos/rabbitmq/api/controllers/__init__.py
delpinos/rabbitmq/api/controllers/enqueue_controller.py
delpinos_rabbitmq_api-0.0.3.dist-info/METADATA
delpinos_rabbitmq_api-0.0.3.dist-info/WHEEL
delpinos_rabbitmq_api-0.0.3.dist-info/top_level.txt
delpinos_rabbitmq_api-0.0.3.dist-info/RECORD
