Metadata-Version: 2.1
Name: delpinos-rabbitmq-api
Version: 0.0.3
Summary: Delpinos Rabbitmq API - Delpinos Framework
Author-email: Alef Bruno Delpino de Oliveira <alef@delpinos.com>
Keywords: delpinos,rabbitmq,api
Classifier: Programming Language :: Python :: 3
Classifier: Programming Language :: Python :: 3.10
Classifier: Topic :: Software Development :: Libraries :: Python Modules
Requires-Python: >=3.10
Requires-Dist: delpinos-rabbitmq >=0.0.4
